{
  "$schema": "https://json-schema.org/draft/2019-09/schema",
  "title": "AlphaNum4",
  "description": "AlphaNum4 is an XDR Struct defined as:\n\n```text struct AlphaNum4 { AssetCode4 assetCode; AccountID issuer; }; ```",
  "type": "object",
  "required": [
    "asset_code",
    "issuer"
  ],
  "properties": {
    "$schema": {
      "type": "string"
    },
    "asset_code": {
      "$ref": "#/definitions/AssetCode4"
    },
    "issuer": {
      "$ref": "#/definitions/AccountId"
    }
  },
  "unevaluatedProperties": false,
  "definitions": {
    "AccountId": {
      "type": "string"
    },
    "AssetCode4": {
      "type": "string"
    }
  }
}