{
  "$schema": "https://json-schema.org/draft/2019-09/schema",
  "title": "ClaimableBalanceEntryExt",
  "description": "ClaimableBalanceEntryExt is an XDR NestedUnion defined as:\n\n```text union switch (int v) { case 0: void; case 1: ClaimableBalanceEntryExtensionV1 v1; } ```",
  "oneOf": [
    {
      "type": "string",
      "enum": [
        "v0"
      ]
    },
    {
      "type": "object",
      "required": [
        "v1"
      ],
      "properties": {
        "v1": {
          "$ref": "#/definitions/ClaimableBalanceEntryExtensionV1"
        }
      }
    }
  ],
  "properties": {
    "$schema": {
      "type": "string"
    }
  },
  "unevaluatedProperties": false,
  "definitions": {
    "ClaimableBalanceEntryExtensionV1": {
      "description": "ClaimableBalanceEntryExtensionV1 is an XDR Struct defined as:\n\n```text struct ClaimableBalanceEntryExtensionV1 { union switch (int v) { case 0: void; } ext;\n\nuint32 flags; // see ClaimableBalanceFlags }; ```",
      "type": "object",
      "required": [
        "ext",
        "flags"
      ],
      "properties": {
        "ext": {
          "$ref": "#/definitions/ClaimableBalanceEntryExtensionV1Ext"
        },
        "flags": {
          "type": "integer",
          "format": "uint32",
          "minimum": 0.0
        }
      }
    },
    "ClaimableBalanceEntryExtensionV1Ext": {
      "description": "ClaimableBalanceEntryExtensionV1Ext is an XDR NestedUnion defined as:\n\n```text union switch (int v) { case 0: void; } ```",
      "type": "string",
      "enum": [
        "v0"
      ]
    }
  }
}